LICENSE
MANIFEST.in
README.md
requirements.txt
setup.py
tests/__init__.py
tests/test.py
xComfortMQTT/__init__.py
xComfortMQTT/__main__.py
xComfortMQTT/config.py
xComfortMQTT/shc_client.py
xComfortMQTT/xComforMqtt.py
xComfortMQTT.egg-info/PKG-INFO
xComfortMQTT.egg-info/SOURCES.txt
xComfortMQTT.egg-info/dependency_links.txt
xComfortMQTT.egg-info/entry_points.txt
xComfortMQTT.egg-info/requires.txt
xComfortMQTT.egg-info/top_level.txt