Metadata-Version: 2.1
Name: xComfortMQTT
Version: 1.1.2
Summary: xComfortMQTT
Home-page: https://github.com/blavka/xComfortMQTT
Author: Karel Blavka
Author-email: karel.blavka@gmail.com
License: MIT
Keywords: cooper influxdb iot
Platform: any
Classifier: Development Status :: 5 - Production/Stable
Classifier: Environment :: Console
Classifier: Intended Audience :: Developers
Classifier: License :: OSI Approved :: MIT License
Classifier: Natural Language :: English
Classifier: Operating System :: OS Independent
Classifier: Programming Language :: Python :: 3
Classifier: Topic :: Utilities
